pyocutil/__init__.py
pyocutil/configs.py
pyocutil/main.py
pyocutil/static.py
pyocutil/utils.py
pyocutil-0.0.2.dist-info/LICENSE
pyocutil-0.0.2.dist-info/METADATA
pyocutil-0.0.2.dist-info/WHEEL
pyocutil-0.0.2.dist-info/entry_points.txt
pyocutil-0.0.2.dist-info/top_level.txt
pyocutil-0.0.2.dist-info/RECORD
