Metadata-Version: 2.1
Name: pyocutil
Version: 0.0.2
Summary: utilities for openshift
Home-page: https://veltzer.github.io/pyocutil
Download-URL: https://github.com/veltzer/pyocutil
Author: Mark Veltzer
Author-email: mark.veltzer@gmail.com
Maintainer: Mark Veltzer
Maintainer-email: mark.veltzer@gmail.com
License: MIT
Keywords: oc,openshift
Platform: python3
Classifier: Development Status :: 4 - Beta
Classifier: Environment :: Console
Classifier: Operating System :: OS Independent
Classifier: Programming Language :: Python
Classifier: Programming Language :: Python :: 3
Classifier: Programming Language :: Python :: 3 :: Only
Classifier: Programming Language :: Python :: 3.11
Classifier: Topic :: Utilities
Classifier: License :: OSI Approved :: MIT License
License-File: LICENSE
Requires-Dist: pytconf
Requires-Dist: pylogconf
